depdf/__init__.py
depdf/api.py
depdf/base.py
depdf/components/__init__.py
depdf/components/image.py
depdf/components/paragraph.py
depdf/components/span.py
depdf/components/table.py
depdf/components/text.py
depdf/config.py
depdf/error.py
depdf/log.py
depdf/page.py
depdf/page_tools.py
depdf/pdf.py
depdf/pdf_tools.py
depdf/settings.py
depdf/utils.py
depdf/version.py
depdf-0.2.2.dist-info/LICENSE
depdf-0.2.2.dist-info/WHEEL
depdf-0.2.2.dist-info/METADATA
depdf-0.2.2.dist-info/RECORD
