Metadata-Version: 2.1
Name: depdf
Version: 0.2.2
Summary: PDF table & paragraph extractor
Home-page: https://github.com/meldonization
License: GPL-3.0-or-later
Keywords: pdf,pdf-parsing,pdf-to-html,table-extraction,paragraph-extraction
Author: Meltonization
Author-email: mengzy1989@gmail.com
Requires-Python: >=3.6,<4.0
Classifier: License :: OSI Approved :: GNU General Public License v3 or later (GPLv3+)
Classifier: Programming Language :: Python :: 3
Classifier: Programming Language :: Python :: 3.6
Classifier: Programming Language :: Python :: 3.7
Classifier: Programming Language :: Python :: 3.8
Classifier: Topic :: Text Processing
Classifier: Topic :: Text Processing :: Markup :: HTML
Classifier: Topic :: Utilities
Requires-Dist: beautifulsoup4 (==4.8.2)
Requires-Dist: pdfplumber (==0.5.16)
Project-URL: Repository, https://github.com/meldonization/depdf
